dqc/__init__.py
dqc/base.py
dqc/crossval.py
dqc/llm.py
dqc/version.py
dqc/crossval_utils/__init__.py
dqc/crossval_utils/_curation.py
dqc/crossval_utils/_dataprocessing.py
dqc/crossval_utils/_sanitychecks.py
dqc/llm_utils/__init__.py
dqc/llm_utils/_sanity_checks.py
dqc/llm_utils/compute_confidence_score.py
dqc/llm_utils/inference.py
dqc/utils/__init__.py
dqc/utils/logging.py
dqc/utils/noise_utils.py
tests/__init__.py
tests/cross_val/__init__.py
tests/cross_val/conftest.py
tests/cross_val/test_crossval.py
tests/llm/__init__.py
tests/llm/conftest.py
tests/llm/test_llm.py
dqc_toolkit-0.2.0.dist-info/LICENSE
dqc_toolkit-0.2.0.dist-info/METADATA
dqc_toolkit-0.2.0.dist-info/WHEEL
dqc_toolkit-0.2.0.dist-info/top_level.txt
dqc_toolkit-0.2.0.dist-info/RECORD
