Metadata-Version: 2.1
Name: dqc-toolkit
Version: 0.2.0
Summary: Data Quality Check for Machine Learning
Author-email: Sumanth S Prabhu <sumanthprabhu.104@gmail.com>
License: MIT License
Project-URL: Homepage, https://github.com/sumanthprabhu/DQC-Toolkit
Project-URL: Source, https://github.com/sumanthprabhu/DQC-Toolkit
Project-URL: Tracker, https://github.com/sumanthprabhu/DQC-Toolkit/issues
Keywords: nlp,data curation,machine learning
Classifier: Intended Audience :: Developers
Classifier: Intended Audience :: Education
Classifier: Intended Audience :: Science/Research
Classifier: License :: OSI Approved :: MIT License
Classifier: Operating System :: MacOS
Classifier: Operating System :: POSIX
Classifier: Operating System :: Unix
Classifier: Programming Language :: Python :: 3
Classifier: Programming Language :: Python :: 3.9
Classifier: Programming Language :: Python :: 3.10
Classifier: Topic :: Scientific/Engineering :: Artificial Intelligence
Requires-Python: >=3.9
License-File: LICENSE
Requires-Dist: transformers >=4.39
Requires-Dist: sentence-transformers >=2.6.1
Requires-Dist: datasets >=2.18
Requires-Dist: accelerate >=0.34.2
Requires-Dist: scikit-learn >=1.3.2
Requires-Dist: ruff >=0.3.4
Provides-Extra: dev
Requires-Dist: pytest >=8.1.1 ; extra == 'dev'
Requires-Dist: mkdocs ==1.5.3 ; extra == 'dev'
Requires-Dist: mkdocs-material ==9.5.17 ; extra == 'dev'
Requires-Dist: mkdocstrings[python] ==0.24.3 ; extra == 'dev'
Requires-Dist: mkdocstrings-crystal ==0.3.7 ; extra == 'dev'
Provides-Extra: docs
Requires-Dist: mkdocs ==1.5.3 ; extra == 'docs'
Requires-Dist: mkdocs-material ==9.5.17 ; extra == 'docs'
Requires-Dist: mkdocstrings[python] ==1.9.2 ; extra == 'docs'
Requires-Dist: mkdocstrings-crystal ==0.3.7 ; extra == 'docs'
Requires-Dist: mike ==2.0.0 ; extra == 'docs'
Provides-Extra: test
Requires-Dist: pytest >=8.1.1 ; extra == 'test'
